mass_dawg.cpython-37m-darwin.so
mass_dawg-1.1.1.dist-info/LICENSE
mass_dawg-1.1.1.dist-info/METADATA
mass_dawg-1.1.1.dist-info/WHEEL
mass_dawg-1.1.1.dist-info/top_level.txt
mass_dawg-1.1.1.dist-info/RECORD
