Metadata-Version: 2.1
Name: mass-dawg
Version: 1.1.1
Summary: A datastructure for efficient storage of mass spectrometry data
Home-page: https://github.com/zmcgrath96/mass_DAWG
Author: Zachary McGrath
Author-email: zmcgrath96@gmail.com
License: UNKNOWN
Keywords: bioinformatics mass_spectrometry ms dawg graph prefix
Platform: UNKNOWN
